attackcti/__init__.py
attackcti/__main__.py
attackcti/attack_api.py
attackcti/cli.py
attackcti/client.py
attackcti/constants.py
attackcti/legacy.py
attackcti/models.py
attackcti/py.typed
attackcti/core/__init__.py
attackcti/core/query_client.py
attackcti/core/objects/__init__.py
attackcti/core/objects/analytics.py
attackcti/core/objects/campaigns.py
attackcti/core/objects/data_sources.py
attackcti/core/objects/detections.py
attackcti/core/objects/groups.py
attackcti/core/objects/mitigations.py
attackcti/core/objects/relationships.py
attackcti/core/objects/software.py
attackcti/core/objects/tactics.py
attackcti/core/objects/techniques.py
attackcti/domains/__init__.py
attackcti/domains/base.py
attackcti/domains/enterprise.py
attackcti/domains/ics.py
attackcti/domains/mobile.py
attackcti/sources/__init__.py
attackcti/sources/attack_source.py
attackcti/sources/local_loader.py
attackcti/sources/resolver.py
attackcti/sources/taxii_loader.py
attackcti/utils/__init__.py
attackcti/utils/downloader.py
attackcti/utils/stix.py
attackcti/utils/storage.py
attackcti-0.6.4.dist-info/METADATA
attackcti-0.6.4.dist-info/WHEEL
attackcti-0.6.4.dist-info/entry_points.txt
attackcti-0.6.4.dist-info/licenses/LICENSE
attackcti-0.6.4.dist-info/RECORD
