Metadata-Version: 2.4
Name: attackcti
Version: 0.6.4
Summary: MITRE ATT&CK CTI Python library
Project-URL: Documentation, https://attackcti.com
Project-URL: Code, https://github.com/OTRF/ATTACK-Python-Client
Project-URL: Issue tracker, https://github.com/OTRF/ATTACK-Python-Client/issues
Author-email: Cyb3rWard0g <9653181+Cyb3rWard0g@users.noreply.github.com>
License: BSD 3-Clause License
License-File: LICENSE
Keywords: cti,cyber threat intelligence,dfir,mitre att&ck,threat hunting
Classifier: Development Status :: 5 - Production/Stable
Classifier: License :: OSI Approved :: BSD License
Classifier: Operating System :: OS Independent
Classifier: Programming Language :: Python :: 3
Classifier: Programming Language :: Python :: 3 :: Only
Classifier: Programming Language :: Python :: 3.9
Classifier: Programming Language :: Python :: 3.10
Classifier: Programming Language :: Python :: 3.11
Classifier: Programming Language :: Python :: 3.12
Classifier: Programming Language :: Python :: 3.13
Classifier: Topic :: Security
Requires-Python: >=3.9
Requires-Dist: pydantic>=2.12.5
Requires-Dist: requests>=2.32.5
Requires-Dist: six>=1.17.0
Requires-Dist: stix2-patterns>=2.0.0
Requires-Dist: stix2>=3.0.1
Requires-Dist: taxii2-client>=2.3.0
Provides-Extra: dev
Requires-Dist: anyio>=4; extra == 'dev'
Requires-Dist: black; extra == 'dev'
Requires-Dist: build; extra == 'dev'
Requires-Dist: packaging; extra == 'dev'
Requires-Dist: pyright>=1.1.407; extra == 'dev'
Requires-Dist: pytest-asyncio>=0.23; extra == 'dev'
Requires-Dist: pytest>=8.4.2; extra == 'dev'
Requires-Dist: ruff>=0.14.6; extra == 'dev'
Requires-Dist: setuptools; extra == 'dev'
Requires-Dist: setuptools-scm; extra == 'dev'
Requires-Dist: twine; extra == 'dev'
Requires-Dist: wheel; extra == 'dev'
